MANIFEST.in
README.rst
setup.py
tplcentral/__init__.py
tplcentral/carriers.py
tplcentral/client.py
tplcentral/customer.py
tplcentral/items.py
tplcentral/orders.py
tplcentral.egg-info/PKG-INFO
tplcentral.egg-info/SOURCES.txt
tplcentral.egg-info/dependency_links.txt
tplcentral.egg-info/requires.txt
tplcentral.egg-info/top_level.txt