Metadata-Version: 1.1
Name: tplcentral
Version: 0.1.2
Summary: 3PL REST API Client
Home-page: https://github.com/candidco/python-tpl
Author: Dhinesh D
Author-email: dvdhinesh.mail@gmail.com
License: MIT
Platform: any
Classifier: Development Status :: 4 - Beta
Classifier: Environment :: Web Environment
Classifier: Intended Audience :: Developers
Classifier: License :: OSI Approved :: MIT License
Classifier: Operating System :: OS Independent
Classifier: Programming Language :: Python :: 2.7
Classifier: Topic :: Internet :: WWW/HTTP :: Dynamic Content
Classifier: Topic :: Software Development :: Libraries :: Python Modules
